{"cameraMode":{"drawMode":0,"name":"Shaded","section":"Shading Mode"},"sceneLighting":true,"audioPlay":false,"sceneViewState":{"m_AlwaysRefresh":false,"showFog":true,"showSkybox":true,"showFlares":true,"showImageEffects":true,"showParticleSystems":true,"showVisualEffectGraphs":true,"m_FxEnabled":true},"in2DMode":false,"pivot":{"x":-92.17308807373047,"y":1.5499999523162842,"z":-60.223785400390628},"rotation":{"x":-0.168324276804924,"y":-0.7577678561210632,"z":0.21506361663341523,"w":-0.5927271842956543},"size":10.0,"orthographic":false}